{
    "name": "Mr Jeon's smart blocks",
    "description": "",
    "dependencies": {
        "core": "*",
        "radio": "*",
        "microphone": "*"
    },
    "files": [
        "main.blocks",
        "main.ts",
        "README.md",
        "docs/play-note-step.md",
        "_locales/en-GB/docs/play-note-step.md",
        "docs/play-continuous-note.md",
        "docs/stop-continuous-music.md"
    ],
    "testFiles": [
        "test.ts"
    ],
    "targetVersions": {
        "target": "8.0.21",
        "targetId": "microbit"
    },
    "supportedTargets": [
        "microbit"
    ],
    "preferredEditor": "tsprj"
}
